required_dict/__init__.py
required_dict/required_dict.py
required_dict-0.26.dist-info/licenses/LICENSE
required_dict-0.26.dist-info/METADATA
required_dict-0.26.dist-info/WHEEL
required_dict-0.26.dist-info/top_level.txt
required_dict-0.26.dist-info/RECORD
