Metadata-Version: 2.4
Name: required_dict
Version: 0.26
Summary: An easy-to-user dictionary validation tool, good for use-cases like POST API data validation.
Author-email: Stephen Hilton <stephen@familyhilton.com>
License-Expression: MIT
Keywords: python,validation,dictionary,dict
Requires-Python: >=3.11
License-File: LICENSE
Dynamic: license-file
